Farama_Notifications/__init__.py
Farama_Notifications-0.0.2.dist-info/LICENSE
Farama_Notifications-0.0.2.dist-info/METADATA
Farama_Notifications-0.0.2.dist-info/WHEEL
Farama_Notifications-0.0.2.dist-info/top_level.txt
Farama_Notifications-0.0.2.dist-info/RECORD
