Metadata-Version: 2.1
Name: Farama-Notifications
Version: 0.0.2
Summary: Notifications for all Farama Foundation maintained libraries.
Home-page: https://github.com/Farama-Foundation/Farama-Notifications
Author: Jordan Terry
Author-email: Jkterry@farama.org
Classifier: Programming Language :: Python :: 3
Classifier: License :: OSI Approved :: MIT License
Classifier: Operating System :: OS Independent
License-File: LICENSE
